itaxotools/__pyinstaller/__init__.py
itaxotools/__pyinstaller/hook-itaxotools.common.py
itaxotools/common/__init__.py
itaxotools/common/bindings.py
itaxotools/common/io.py
itaxotools/common/machine.py
itaxotools/common/threading.py
itaxotools/common/types.py
itaxotools/common/utility.py
itaxotools/common/param/__init__.py
itaxotools/common/param/core.py
itaxotools/common/param/model.py
itaxotools/common/param/view.py
itaxotools/common/resources/__init__.py
itaxotools/common/resources/icons/svg/arrow-right.svg
itaxotools/common/resources/icons/svg/clear.svg
itaxotools/common/resources/icons/svg/export.svg
itaxotools/common/resources/icons/svg/home.svg
itaxotools/common/resources/icons/svg/open.svg
itaxotools/common/resources/icons/svg/run.svg
itaxotools/common/resources/icons/svg/save.svg
itaxotools/common/resources/icons/svg/save_all.svg
itaxotools/common/resources/icons/svg/search.svg
itaxotools/common/resources/icons/svg/stop.svg
itaxotools/common/resources/logos/itaxotools-logo-64px.png
itaxotools/common/resources/logos/itaxotools-micrologo.png
itaxotools/common/widgets/__init__.py
itaxotools/common/widgets/dialogs.py
itaxotools/common/widgets/graphics.py
itaxotools/common/widgets/layouts.py
itaxotools/common/widgets/widgets.py
itaxotools_common-0.3.5.dist-info/licenses/LICENSE.txt
itaxotools_common-0.3.5.dist-info/METADATA
itaxotools_common-0.3.5.dist-info/WHEEL
itaxotools_common-0.3.5.dist-info/entry_points.txt
itaxotools_common-0.3.5.dist-info/top_level.txt
itaxotools_common-0.3.5.dist-info/RECORD
